{
  "project_info": {
    "project_number": "775100362040",
    "firebase_url": "https://complaint-register-4227e.firebaseio.com",
    "project_id": "complaint-register-4227e",
    "storage_bucket": "complaint-register-4227e.appspot.com"
  },
  "client": [
    {
      "client_info": {
        "mobilesdk_app_id": "1:775100362040:android:53beac32afb38f43b7e5cd",
        "android_client_info": {
          "package_name": "com.example.complaintregister"
        }
      },
      "oauth_client": [
        {
          "client_id": "775100362040-mkvustpmiat97ikdrrctva8p48i7erkl.apps.googleusercontent.com",
          "client_type": 1,
          "android_info": {
            "package_name": "com.example.complaintregister",
            "certificate_hash": "417a4866274957ebb818617011bac67ed3c2e8b2"
          }
        },
        {
          "client_id": "775100362040-2u7cskre6rt24b0p5kqjo946eob1gtnj.apps.googleusercontent.com",
          "client_type": 3
        }
      ],
      "api_key": [
        {
          "current_key": "AIzaSyBtJ9xZPt-RCf92kbh5irdUJ0oUrUrcJig"
        }
      ],
      "services": {
        "appinvite_service": {
          "other_platform_oauth_client": [
            {
              "client_id": "775100362040-2u7cskre6rt24b0p5kqjo946eob1gtnj.apps.googleusercontent.com",
              "client_type": 3
            }
          ]
        }
      }
    }
  ],
  "configuration_version": "1"
}